[
  {
    "at": "2026-05-26T20:08:27.049Z",
    "decisionId": 104,
    "verdict": "ACCEPTED",
    "checks": [
      {
        "name": "price_freshness",
        "status": "PASS"
      },
      {
        "name": "drift_detection",
        "status": "PASS"
      }
    ],
    "blockReason": null
  },
  {
    "at": "2026-05-26T22:19:34.756Z",
    "decisionId": 105,
    "verdict": "ACCEPTED",
    "checks": [
      {
        "name": "price_freshness",
        "status": "PASS"
      },
      {
        "name": "drift_detection",
        "status": "PASS"
      }
    ],
    "blockReason": null
  },
  {
    "at": "2026-05-27T00:03:54.803Z",
    "decisionId": 106,
    "verdict": "ACCEPTED",
    "checks": [
      {
        "name": "price_freshness",
        "status": "PASS"
      },
      {
        "name": "drift_detection",
        "status": "PASS"
      }
    ],
    "blockReason": null
  },
  {
    "at": "2026-05-27T05:14:47.755Z",
    "decisionId": 107,
    "verdict": "ACCEPTED",
    "checks": [
      {
        "name": "price_freshness",
        "status": "PASS"
      },
      {
        "name": "drift_detection",
        "status": "PASS"
      }
    ],
    "blockReason": null
  },
  {
    "at": "2026-05-27T09:44:22.865Z",
    "decisionId": 108,
    "verdict": "ACCEPTED",
    "checks": [
      {
        "name": "tx_proof",
        "status": "SKIP"
      },
      {
        "name": "price_freshness",
        "status": "PASS"
      },
      {
        "name": "drift_detection",
        "status": "PASS"
      }
    ],
    "blockReason": null
  },
  {
    "at": "2026-05-27T12:53:06.084Z",
    "decisionId": 109,
    "verdict": "ACCEPTED",
    "checks": [
      {
        "name": "tx_proof",
        "status": "SKIP"
      },
      {
        "name": "price_freshness",
        "status": "PASS"
      },
      {
        "name": "drift_detection",
        "status": "PASS"
      }
    ],
    "blockReason": null
  },
  {
    "at": "2026-05-27T16:05:47.179Z",
    "decisionId": 110,
    "verdict": "ACCEPTED",
    "checks": [
      {
        "name": "tx_proof",
        "status": "SKIP"
      },
      {
        "name": "price_freshness",
        "status": "PASS"
      },
      {
        "name": "drift_detection",
        "status": "PASS"
      }
    ],
    "blockReason": null
  },
  {
    "at": "2026-05-27T16:37:31.325Z",
    "decisionId": 111,
    "verdict": "ACCEPTED",
    "checks": [
      {
        "name": "tx_proof",
        "status": "SKIP"
      },
      {
        "name": "price_freshness",
        "status": "PASS"
      },
      {
        "name": "drift_detection",
        "status": "PASS"
      }
    ],
    "blockReason": null
  },
  {
    "at": "2026-05-27T17:18:52.199Z",
    "decisionId": 112,
    "verdict": "ACCEPTED",
    "checks": [
      {
        "name": "price_freshness",
        "status": "PASS"
      },
      {
        "name": "drift_detection",
        "status": "PASS"
      }
    ],
    "blockReason": null
  }
]
