{
  "cycleStartedAt": "2026-05-27T19:24:15.011Z",
  "cycleEndedAt": "2026-05-27T19:25:33.098Z",
  "durationSeconds": 78.09,
  "decisionId": 113,
  "decisionTier": "BLOCKED_BY_LOW_CONFIDENCE",
  "consensus": false,
  "txHashes": [
    "0xff1dbce57a36c3ee73a8b6c86a81198965187f5a7005a3b7775d7fbaef303bd9"
  ],
  "ipfsCid": null,
  "mode": "cron-github-actions",
  "githubRunUrl": "https://github.com/USBVadik/TuringVault-Core/actions/runs/26533540802",
  "errors": [],
  "rwa": {
    "source": "conservative",
    "executed": true,
    "amountInUsd": 5,
    "from": "USDT",
    "to": "USDT0",
    "blockedReason": null
  }
}
