{
  "cycleStartedAt": "2026-06-05T10:54:19.813Z",
  "cycleEndedAt": "2026-06-05T10:55:23.454Z",
  "durationSeconds": 63.64,
  "stageTiming": {
    "marketDataMs": null,
    "analystMs": 3754,
    "validatorMs": 6840,
    "arbiterMs": null,
    "onChainMs": null,
    "ipfsMs": null,
    "rwaMs": null
  },
  "decisionId": 306,
  "decisionTier": "BLOCKED_BY_REGIME",
  "consensus": false,
  "txHashes": [],
  "ipfsCid": null,
  "mode": "cron-github-actions",
  "githubRunUrl": "https://github.com/USBVadik/TuringVault-Core/actions/runs/27010753860",
  "errors": [],
  "gridTradeCandidate": {
    "active": false,
    "kind": null,
    "action": null,
    "direction": null,
    "targetAsset": null,
    "sourceAsset": null,
    "allocationPct": null,
    "confidence": null,
    "reason": "regime TREND_DOWN does not allow grid risk-on",
    "routeHint": null
  },
  "executionStatus": "BLOCKED_BY_REGIME"
}
