{
  "cycleStartedAt": "2026-06-06T18:41:55.831Z",
  "cycleEndedAt": "2026-06-06T18:43:08.979Z",
  "durationSeconds": 73.15,
  "stageTiming": {
    "marketDataMs": null,
    "analystMs": 18270,
    "validatorMs": 6959,
    "arbiterMs": null,
    "onChainMs": null,
    "ipfsMs": null,
    "rwaMs": null
  },
  "decisionId": 341,
  "decisionTier": "BLOCKED_BY_REGIME",
  "consensus": false,
  "txHashes": [],
  "ipfsCid": null,
  "mode": "cron-github-actions",
  "githubRunUrl": "https://github.com/USBVadik/TuringVault-Core/actions/runs/27070660961",
  "errors": [],
  "gridTradeCandidate": {
    "active": false,
    "kind": null,
    "action": null,
    "direction": null,
    "targetAsset": null,
    "sourceAsset": null,
    "allocationPct": null,
    "confidence": null,
    "reason": "not stable-heavy FLAT inventory",
    "routeHint": null
  },
  "executionStatus": "BLOCKED_BY_REGIME"
}
